{
  "id": "ds-ending-betrayal",
  "region": "dawn-spire",
  "type": "ending",
  "description": "검을 내린다. 손가락이 풀린다.\n\n마왕의 눈이 너를 본다. 한 박자도 흔들리지 않는다.\n\n마왕: \"...너도 같은 길을 갔구나.\"\n\n회색의 자가 등을 돌린다. 그는 다시는 너를 보지 않는다.\n\n옥좌가 너를 받아들인다. 차가운 돌이 어깨에 맞는다 — 오래 비어 있던 자리가 형태를 기억하듯.\n\n마왕의 그림자가 옅어진다. 너의 그림자가 길어진다.\n\n옥좌의 차가움이 어깨에 그대로 머문다.",
  "echoes": [
    {
      "condition": { "knowledge": "fled-corrupted" },
      "text": "광기 부대의 음절은 더는 등 뒤에서 따라오지 않는다. 이제 그 음절이 네 아래에서 올라온다."
    },
    {
      "condition": { "knowledge": "mirror-self" },
      "text": "거울 속 한 걸음 짧던 네 모습이 옥좌 위에서 마침내 너와 같은 길이가 된다."
    },
    {
      "condition": { "knowledge": "chose-leave" },
      "text": "꿈꾸는 도시의 문을 닫고 나왔던 손이 이번에는 옥좌실 문을 안쪽에서 닫는다."
    }
  ],
  "choices": []
}
