{
  "id": "ds-floor-illusion-fight",
  "region": "dawn-spire",
  "type": "combat",
  "enemyId": "demon-king-lieutenant",
  "description": "환영이 더 짙어진다. 푸른 불 사이에서 마왕 군세의 장수 하나가 걸어 나온다.\n\n낡은 갑옷에는 검은 명령의 흔적이 말라붙어 있다. 투구 안쪽의 눈이 너를 붙든다.\n\n환영이어도 칼끝은 무겁다.",
  "choices": [
    {
      "id": "engage",
      "text": "환영을 마주한다",
      "startsCombat": true,
      "outcome": {
        "text": "푸른 불이 흔들린다. 장수의 갑옷이 네 발 앞에서 무게를 잡는다.",
        "nextNodeId": null
      }
    },
    {
      "id": "evade",
      "text": "옆으로 빠진다",
      "startsCombat": false,
      "outcome": {
        "text": "환영의 틈으로 한 걸음 비낀다. 장수의 칼이 옆구리를 스치고 빠진다. 투구 안쪽의 눈도 너를 끝까지 붙잡지 못한다.\n\n푸른 불이 장수의 등 뒤에 머문다.",
        "statDelta": { "hp": -1 },
        "nextNodeId": "ds-floor-strangers"
      }
    },
    {
      "id": "illusion-fight-cut",
      "text": "환영을 가른다",
      "outcome": {
        "text": "검이 갑옷에 박힌다. 환영은 흩어지지 않는다. 그 자리에서 무게를 잃고 무너진다. 푸른 불이 조금 흐려진다.",
        "statDelta": { "hp": -2 },
        "enemyDamage": 8,
        "nextNodeId": "ds-floor-strangers"
      }
    },
    {
      "id": "illusion-fight-rune",
      "text": "룬으로 환영을 끊는다",
      "outcome": {
        "text": "룬을 그린다. 환영의 윤곽이 흔들리고, 장수의 몸이 옆으로 밀린다. 칼은 허공을 가르고, 갑옷은 푸른 불 안으로 주저앉는다.",
        "statDelta": { "mana": -2 },
        "enemyDamage": 8,
        "knowledgeGain": ["old-ages"],
        "nextNodeId": "ds-floor-strangers"
      }
    }
  ]
}
